bscache/__init__.py
bscache/cache.py
bscache/cache_old.py
bscache/cli.py
bscache-2.0.0.dist-info/DESCRIPTION.rst
bscache-2.0.0.dist-info/METADATA
bscache-2.0.0.dist-info/RECORD
bscache-2.0.0.dist-info/WHEEL
bscache-2.0.0.dist-info/entry_points.txt
bscache-2.0.0.dist-info/metadata.json
bscache-2.0.0.dist-info/top_level.txt
