Metadata-Version: 2.0
Name: bscache
Version: 2.0.0
Summary: create Steam cache for project the BattleSrv
Home-page: https://github.com/k0st1an/bscache
Author: Konstantin Kruglov
Author-email: kruglovk@gmail.com
License: Apache License Version 2.0
Platform: UNKNOWN
Classifier: Development Status :: 3 - Alpha
Classifier: License :: OSI Approved :: Apache Software License
Classifier: Programming Language :: Python :: 3 :: Only
Classifier: Operating System :: POSIX :: Linux
Requires-Dist: hedgehog (>=0.2.2)
Requires-Dist: click (==6.7)
Requires-Dist: bsconf (>=0.0.2)
